dswizard/components/__init__.py
dswizard/components/base.py
dswizard/components/meta_features.py
dswizard/components/sklearn.py
dswizard/components/util.py
dswizard/components/classification/__init__.py
dswizard/components/classification/ada_boosting.py
dswizard/components/classification/bernoulli_nb.py
dswizard/components/classification/decision_tree.py
dswizard/components/classification/gradient_boosting.py
dswizard/components/classification/libsvm_svc.py
dswizard/components/classification/linear_discriminant_analysis.py
dswizard/components/classification/multinomial_nb.py
dswizard/components/classification/random_forest.py
dswizard/components/classification/sgd.py
dswizard/components/classification/excluded/__init__.py
dswizard/components/classification/excluded/extra_trees.py
dswizard/components/classification/excluded/gaussian_nb.py
dswizard/components/classification/excluded/gaussian_process.py
dswizard/components/classification/excluded/k_neighbors.py
dswizard/components/classification/excluded/logistic_regression.py
dswizard/components/classification/excluded/mlp_classifier.py
dswizard/components/classification/excluded/passive_aggressive.py
dswizard/components/classification/excluded/qda.py
dswizard/components/classification/excluded/svm.py
dswizard/components/data_preprocessing/__init__.py
dswizard/components/data_preprocessing/imputation.py
dswizard/components/data_preprocessing/knn_imputer.py
dswizard/components/data_preprocessing/max_abs_scaler.py
dswizard/components/data_preprocessing/minmax.py
dswizard/components/data_preprocessing/normalize.py
dswizard/components/data_preprocessing/quantile_transformer.py
dswizard/components/data_preprocessing/robust_scaler.py
dswizard/components/data_preprocessing/standard_scaler.py
dswizard/components/data_preprocessing/test/__init__.py
dswizard/components/data_preprocessing/test/openml14_conditional_imputer.py
dswizard/components/feature_preprocessing/__init__.py
dswizard_components-0.1.1.dist-info/METADATA
dswizard_components-0.1.1.dist-info/WHEEL
dswizard_components-0.1.1.dist-info/top_level.txt
dswizard_components-0.1.1.dist-info/RECORD
