Metadata-Version: 2.1
Name: dswizard-components
Version: 0.1.1
Summary: Contains all base algorithms used by dswizard
Home-page: https://github.com/Ennosigaeon/dswizard-components
Author: Marc Zoeller
Author-email: m.zoeller@usu.de
License: MIT
Keywords: automl,machine learning,pipeline synthesis
Platform: UNKNOWN
Classifier: License :: OSI Approved :: MIT License
Classifier: Programming Language :: Python :: 3
Classifier: Programming Language :: Python :: 3.5
Requires-Python: >=3.5
Requires-Dist: psutil (==5.7.2)
Requires-Dist: pymfe (==0.4.*)
Requires-Dist: ConfigSpace (==0.4.*)
Requires-Dist: numpy (==1.19.*)
Requires-Dist: pandas (==1.1.*)
Requires-Dist: pytest
Requires-Dist: scikit-learn (==0.23.*)
Requires-Dist: scipy (==1.5.*)
